useer/__init__.py
useer/pysparklib/__init__.py
useer/pysparklib/exceptions.py
useer/pysparklib/ml/__init__.py
useer/pysparklib/pmml/__init__.py
useer/utils/__init__.py
useer/utils/demo.py
useer/utils/seer_util.py
useer-0.0.6.dist-info/LICENSE
useer-0.0.6.dist-info/METADATA
useer-0.0.6.dist-info/WHEEL
useer-0.0.6.dist-info/top_level.txt
useer-0.0.6.dist-info/RECORD
