Metadata-Version: 2.1
Name: useer
Version: 0.0.6
Summary: A elaborate and developed PySpark libraries and resources.
Home-page: https://github.com/466697790/useer
Author: liujinzhou
Author-email: 466697790@qq.com
License: MIT License
Keywords: apache,spark,sparkML,pmml
Classifier: Development Status :: 5 - Production/Stable
Classifier: Intended Audience :: Developers
Classifier: Natural Language :: Chinese (Simplified)
Classifier: License :: OSI Approved :: Apache Software License
Classifier: Programming Language :: Python
Classifier: Programming Language :: Python :: 3.7
Classifier: Programming Language :: Python :: Implementation :: PyPy
Classifier: Topic :: Software Development :: Libraries :: Python Modules
Requires-Python: >=3.7
License-File: LICENSE
